autocoder/__init__.py
autocoder/auto_coder.py
autocoder/auto_coder_rag.py
autocoder/auto_coder_runner.py
autocoder/auto_coder_terminal.py
autocoder/auto_coder_terminal_v3.py
autocoder/chat_auto_coder.py
autocoder/chat_auto_coder_lang.py
autocoder/command_args.py
autocoder/lang.py
autocoder/models.py
autocoder/rags.py
autocoder/run_context.py
autocoder/version.py
autocoder/agent/__init__.py
autocoder/agent/auto_demand_organizer.py
autocoder/agent/auto_filegroup.py
autocoder/agent/auto_guess_query.py
autocoder/agent/auto_learn.py
autocoder/agent/auto_learn_from_commit.py
autocoder/agent/auto_review_commit.py
autocoder/agent/auto_tool.py
autocoder/agent/coder.py
autocoder/agent/designer.py
autocoder/agent/planner.py
autocoder/agent/project_reader.py
autocoder/agent/base_agentic/__init__.py
autocoder/agent/base_agentic/agent_hub.py
autocoder/agent/base_agentic/agentic_lang.py
autocoder/agent/base_agentic/agentic_tool_display.py
autocoder/agent/base_agentic/base_agent.py
autocoder/agent/base_agentic/default_tools.py
autocoder/agent/base_agentic/test_base_agent.py
autocoder/agent/base_agentic/tool_registry.py
autocoder/agent/base_agentic/types.py
autocoder/agent/base_agentic/utils.py
autocoder/agent/base_agentic/tools/__init__.py
autocoder/agent/base_agentic/tools/ask_followup_question_tool_resolver.py
autocoder/agent/base_agentic/tools/attempt_completion_tool_resolver.py
autocoder/agent/base_agentic/tools/base_tool_resolver.py
autocoder/agent/base_agentic/tools/example_tool_resolver.py
autocoder/agent/base_agentic/tools/execute_command_tool_resolver.py
autocoder/agent/base_agentic/tools/list_files_tool_resolver.py
autocoder/agent/base_agentic/tools/plan_mode_respond_tool_resolver.py
autocoder/agent/base_agentic/tools/read_file_tool_resolver.py
autocoder/agent/base_agentic/tools/replace_in_file_tool_resolver.py
autocoder/agent/base_agentic/tools/search_files_tool_resolver.py
autocoder/agent/base_agentic/tools/talk_to_group_tool_resolver.py
auto_coder-2.0.44.dist-info/LICENSE
auto_coder-2.0.44.dist-info/METADATA
auto_coder-2.0.44.dist-info/WHEEL
auto_coder-2.0.44.dist-info/entry_points.txt
auto_coder-2.0.44.dist-info/top_level.txt
auto_coder-2.0.44.dist-info/RECORD
